invenio_subjects_nasa/__init__.py
invenio_subjects_nasa/config.py
invenio_subjects_nasa/convert_data.py
invenio_subjects_nasa/utils.py
invenio_subjects_nasa/downloads/thesaurus-CSV-2025-09-17.csv
invenio_subjects_nasa/vocabularies/__init__.py
invenio_subjects_nasa/vocabularies/nasa_thesaurus.yaml
invenio_subjects_nasa/vocabularies/vocabularies.yaml
invenio_subjects_nasa-2.1.0.dist-info/METADATA
invenio_subjects_nasa-2.1.0.dist-info/WHEEL
invenio_subjects_nasa-2.1.0.dist-info/entry_points.txt
invenio_subjects_nasa-2.1.0.dist-info/RECORD
