Metadata-Version: 2.4
Name: invenio-subjects-nasa
Version: 2.1.0
Summary: invenio_subjects_nasa vocabularies
Project-URL: Homepage, https://github.com/Samk13/invenio-subjects-nasa
Project-URL: Repository, https://github.com/Samk13/invenio-subjects-nasa
Project-URL: Issues, https://github.com/Samk13/invenio-subjects-nasa/issues
Author-email: KTH Royal Institute of Technology <info@kth.se>
License: MIT
Keywords: invenio,nasa,vocabularies
Classifier: Intended Audience :: Developers
Classifier: License :: OSI Approved :: MIT License
Classifier: Operating System :: OS Independent
Classifier: Programming Language :: Python
Classifier: Programming Language :: Python :: 3
Classifier: Programming Language :: Python :: 3.9
Classifier: Programming Language :: Python :: 3.10
Classifier: Programming Language :: Python :: 3.11
Classifier: Programming Language :: Python :: 3.12
Classifier: Programming Language :: Python :: 3.13
Requires-Python: >=3.9
Provides-Extra: tests
Requires-Dist: pytest-invenio>=2.1.7; extra == 'tests'
Requires-Dist: pytest>=7.0.0; extra == 'tests'
Requires-Dist: pyyaml>=6.0.1; extra == 'tests'
Requires-Dist: ruff>=0.1.0; extra == 'tests'
Requires-Dist: wheel>=0.42.0; extra == 'tests'
